{
  "android.support.annotation" : [ "AnimRes", "AnimatorRes", "AnyRes", "AnyThread", "ArrayRes", "AttrRes", "BinderThread", "BoolRes", "CallSuper", "CheckResult", "ColorInt", "ColorRes", "DimenRes", "Dimension", "DrawableRes", "FloatRange", "FractionRes", "IdRes", "IntDef", "IntRange", "IntegerRes", "InterpolatorRes", "Keep", "LayoutRes", "MainThread", "MenuRes", "NonNull", "Nullable", "PluralsRes", "Px", "RawRes", "RequiresApi", "RequiresPermission", "RequiresPermission$Read", "RequiresPermission$Write", "RestrictTo", "RestrictTo$Scope", "Size", "StringDef", "StringRes", "StyleRes", "StyleableRes", "TransitionRes", "UiThread", "VisibleForTesting", "WorkerThread", "XmlRes" ],
  "jp.kshoji.driver.midi" : [ "BuildConfig", "R", "R$xml" ],
  "jp.kshoji.driver.midi.activity" : [ "AbstractMultipleMidiActivity", "AbstractMultipleMidiActivity$OnMidiDeviceAttachedListenerImpl", "AbstractMultipleMidiActivity$OnMidiDeviceAttachedListenerImpl$1", "AbstractMultipleMidiActivity$OnMidiDeviceAttachedListenerImpl$2", "AbstractMultipleMidiActivity$OnMidiDeviceDetachedListenerImpl", "AbstractMultipleMidiActivity$OnMidiDeviceDetachedListenerImpl$1", "AbstractMultipleMidiActivity$OnMidiDeviceDetachedListenerImpl$2", "AbstractSingleMidiActivity", "AbstractSingleMidiActivity$OnMidiDeviceAttachedListenerImpl", "AbstractSingleMidiActivity$OnMidiDeviceAttachedListenerImpl$1", "AbstractSingleMidiActivity$OnMidiDeviceAttachedListenerImpl$2", "AbstractSingleMidiActivity$OnMidiDeviceDetachedListenerImpl", "AbstractSingleMidiActivity$OnMidiDeviceDetachedListenerImpl$1", "AbstractSingleMidiActivity$OnMidiDeviceDetachedListenerImpl$2", "MidiFragmentHostActivity", "MidiFragmentHostActivity$OnMidiDeviceAttachedListenerImpl", "MidiFragmentHostActivity$OnMidiDeviceAttachedListenerImpl$1", "MidiFragmentHostActivity$OnMidiDeviceAttachedListenerImpl$2", "MidiFragmentHostActivity$OnMidiDeviceDetachedListenerImpl", "MidiFragmentHostActivity$OnMidiDeviceDetachedListenerImpl$1", "MidiFragmentHostActivity$OnMidiDeviceDetachedListenerImpl$2" ],
  "jp.kshoji.driver.midi.device" : [ "MidiDeviceConnectionWatcher", "MidiDeviceConnectionWatcher$1", "MidiDeviceConnectionWatcher$1$1", "MidiDeviceConnectionWatcher$MidiDeviceConnectionWatchThread", "MidiDeviceConnectionWatcher$UsbMidiGrantedReceiver", "MidiInputDevice", "MidiInputDevice$WaiterThread", "MidiOutputDevice", "MidiOutputDevice$WaiterThread" ],
  "jp.kshoji.driver.midi.fragment" : [ "AbstractMidiFragment" ],
  "jp.kshoji.driver.midi.listener" : [ "OnMidiDeviceAttachedListener", "OnMidiDeviceDetachedListener", "OnMidiInputEventListener" ],
  "jp.kshoji.driver.midi.sample" : [ "BuildConfig", "MIDIDriverMultipleSampleActivity", "MIDIDriverMultipleSampleActivity$1", "MIDIDriverMultipleSampleActivity$2", "MIDIDriverMultipleSampleActivity$3", "MIDIDriverMultipleSampleActivity$4", "MIDIDriverSingleSampleActivity", "MIDIDriverSingleSampleActivity$1", "MIDIDriverSingleSampleActivity$2", "MIDIDriverSingleSampleActivity$3", "MIDIDriverSingleSampleActivity$4", "R", "R$array", "R$attr", "R$drawable", "R$id", "R$layout", "R$string", "R$xml", "UsbMidiDriverSampleActivity", "UsbMidiDriverSampleActivity$1", "UsbMidiDriverSampleActivity$2", "UsbMidiDriverSampleActivity$3", "UsbMidiDriverSampleActivity$3$1", "UsbMidiDriverSampleActivity$3$2", "UsbMidiDriverSampleActivity$4", "UsbMidiDriverSampleActivity$5" ],
  "jp.kshoji.driver.midi.sample.util" : [ "SoundMaker", "Tone" ],
  "jp.kshoji.driver.midi.service" : [ "MultipleMidiService", "MultipleMidiService$1", "MultipleMidiService$2", "MultipleMidiService$LocalBinder", "SingleMidiService", "SingleMidiService$1", "SingleMidiService$2", "SingleMidiService$3", "SingleMidiService$LocalBinder" ],
  "jp.kshoji.driver.midi.util" : [ "Constants", "ReusableByteArrayOutputStream", "UsbMidiDeviceUtils", "UsbMidiDriver", "UsbMidiDriver$OnMidiDeviceAttachedListenerImpl", "UsbMidiDriver$OnMidiDeviceDetachedListenerImpl" ],
  "jp.kshoji.driver.usb.util" : [ "DeviceFilter" ],
  "jp.kshoji.javax.sound.midi" : [ "ControllerEventListener", "Instrument", "InvalidMidiDataException", "MetaEventListener", "MetaMessage", "MidiChannel", "MidiDevice", "MidiDevice$Info", "MidiDeviceReceiver", "MidiDeviceTransmitter", "MidiEvent", "MidiFileFormat", "MidiMessage", "MidiSystem", "MidiSystem$MidiSystemUtils", "MidiUnavailableException", "Patch", "Receiver", "Sequence", "Sequencer", "Sequencer$SyncMode", "ShortMessage", "Soundbank", "SoundbankResource", "Synthesizer", "SysexMessage", "Track", "Track$1", "Track$TrackUtils", "Transmitter", "UsbMidiSystem", "VoiceStatus" ],
  "jp.kshoji.javax.sound.midi.impl" : [ "MidiChannelImpl", "SequencerImpl", "SequencerImpl$1", "SequencerImpl$SequencerThread", "SequencerImpl$SequencerThread$1" ],
  "jp.kshoji.javax.sound.midi.io" : [ "StandardMidiFileReader", "StandardMidiFileReader$ExtendedMidiFileFormat", "StandardMidiFileReader$MidiDataInputStream", "StandardMidiFileWriter", "StandardMidiFileWriter$MidiDataOutputStream" ],
  "jp.kshoji.javax.sound.midi.spi" : [ "MidiDeviceProvider", "MidiFileReader", "MidiFileWriter", "SoundbankReader" ],
  "jp.kshoji.javax.sound.midi.usb" : [ "UsbMidiDevice", "UsbMidiReceiver", "UsbMidiSynthesizer", "UsbMidiTransmitter", "UsbMidiTransmitter$OnMidiInputEventListenerImpl" ],
  "jp.kshoji.javax_sound_midi" : [ "BuildConfig", "R" ]
}